ionical/__init__.py
ionical/__main__.py
ionical/ionical.py
ionical-0.5.13.dist-info/LICENCE
ionical-0.5.13.dist-info/METADATA
ionical-0.5.13.dist-info/WHEEL
ionical-0.5.13.dist-info/entry_points.txt
ionical-0.5.13.dist-info/top_level.txt
ionical-0.5.13.dist-info/RECORD
