Metadata-Version: 2.1
Name: ionical
Version: 0.5.13
Summary: command line tool for tracking ical changes
Home-page: https://github.com/danyul/ionical
Author: Daniel Langsam
Author-email: dangit@langsam.org
License: MIT
Keywords: icalendar,ics,schedule,changelog,amion,gcal,google,calendar
Platform: UNKNOWN
Classifier: Natural Language :: English
Classifier: Programming Language :: Python :: 3.6
Requires-Dist: icalendar
Requires-Dist: pytz
Requires-Dist: recurring-ical-events
Requires-Dist: toml
Provides-Extra: dev
Requires-Dist: black ; extra == 'dev'
Requires-Dist: mypy ; extra == 'dev'
Requires-Dist: flake8 ; extra == 'dev'
Requires-Dist: flake8-import-order ; extra == 'dev'
Requires-Dist: sphinx (==3.3.1) ; extra == 'dev'
Requires-Dist: recommonmark ; extra == 'dev'
Requires-Dist: pytest ; extra == 'dev'
Provides-Extra: test
Requires-Dist: pytest ; extra == 'test'
